<?xml version="1.0" encoding="UTF-8"?><TokenMakerDefinition>
  <general>
    <package>kp.ps.editor</package>
    <className>PopScriptHighlight</className>
    <extendedClass>AbstractJFlexCTokenMaker</extendedClass>
    <classComment/>
    <ignoreCase>false</ignoreCase>
    <booleanLiterals>false</booleanLiterals>
  </general>
  <comments>
    <lineComments enabled="true" start="//"/>
    <multiLineComments enabled="true" end="*/" start="/*"/>
    <docComments enabled="false" end="" start=""/>
  </comments>
  <keywords>
    <keyword>const</keyword>
    <keyword>else</keyword>
    <keyword>every</keyword>
    <keyword>if</keyword>
    <keyword>import</keyword>
    <keyword>init</keyword>
    <keyword>internal</keyword>
    <keyword>macro</keyword>
    <keyword>main</keyword>
    <keyword>namespace</keyword>
    <keyword>off</keyword>
    <keyword>on</keyword>
    <keyword>var</keyword>
    <keyword>yield</keyword>
  </keywords>
  <keywords2>
    <keyword>AIRSHIP_HUT</keyword>
    <keyword>AIRSHIP_HUT_2</keyword>
    <keyword>ANGEL_OF_DEAD</keyword>
    <keyword>ATTACK_BUILDING</keyword>
    <keyword>ATTACK_BY_BALLON</keyword>
    <keyword>ATTACK_BY_BOAT</keyword>
    <keyword>ATTACK_MARKER</keyword>
    <keyword>ATTACK_NORMAL</keyword>
    <keyword>ATTACK_PERSON</keyword>
    <keyword>ATTR_ATTACK_PERCENTAGE</keyword>
    <keyword>ATTR_AWAY_BRAVE</keyword>
    <keyword>ATTR_AWAY_FIREWARRIOR</keyword>
    <keyword>ATTR_AWAY_RELIGIOUS</keyword>
    <keyword>ATTR_AWAY_SHAMAN</keyword>
    <keyword>ATTR_AWAY_SPY</keyword>
    <keyword>ATTR_AWAY_WARRIOR</keyword>
    <keyword>ATTR_BASE_UNDER_ATTACK_RETREAT</keyword>
    <keyword>ATTR_BOAT_HOUSE_BROKEN</keyword>
    <keyword>ATTR_COUNT_PREACH_DAMAGE</keyword>
    <keyword>ATTR_DEFENSE_RAD_INCR</keyword>
    <keyword>ATTR_DONT_AUTO_TRAIN_PREACHERS</keyword>
    <keyword>ATTR_DONT_DELETE_USELESS_BOAT_HOUSE</keyword>
    <keyword>ATTR_DONT_GROUP_AT_DT</keyword>
    <keyword>ATTR_DONT_USE_BOATS</keyword>
    <keyword>ATTR_EMPTY_AT_WAYPOING</keyword>
    <keyword>ATTR_ENEMY_SPY_MAX_STAND</keyword>
    <keyword>ATTR_EXPANSION</keyword>
    <keyword>ATTR_FIGHT_STOP_DISTANCE</keyword>
    <keyword>ATTR_GROUP_OPTION</keyword>
    <keyword>ATTR_HOUSE_PERCENTAGE</keyword>
    <keyword>ATTR_MAX_ATTACKS</keyword>
    <keyword>ATTR_MAX_BUILDINGS_ON_GO</keyword>
    <keyword>ATTR_MAX_DEFENSIVE_ACTIONS</keyword>
    <keyword>ATTR_MAX_SPY_ATTACKS</keyword>
    <keyword>ATTR_MAX_TRAIN_AT_ONCE</keyword>
    <keyword>ATTR_PEOPLE_PER_BALLON</keyword>
    <keyword>ATTR_PEOPLE_PER_BOAT</keyword>
    <keyword>ATTR_PREF_BALLON_DRIVERS</keyword>
    <keyword>ATTR_PREF_BALLON_HUTS</keyword>
    <keyword>ATTR_PREF_BOAT_DRIVERS</keyword>
    <keyword>ATTR_PREF_BOAT_HUTS</keyword>
    <keyword>ATTR_PREF_FIREWARRIOR_PEOPLE</keyword>
    <keyword>ATTR_PREF_FIREWARRIOR_TRAINS</keyword>
    <keyword>ATTR_PREF_RELIGIOUS_PEOPLE</keyword>
    <keyword>ATTR_PREF_RELIGIOUS_TRAINS</keyword>
    <keyword>ATTR_PREF_SPY_PEOPLE</keyword>
    <keyword>ATTR_PREF_SPY_TRAINS</keyword>
    <keyword>ATTR_PREF_WARRIOR_PEOPLE</keyword>
    <keyword>ATTR_PREF_WARRIOR_TRAINS</keyword>
    <keyword>ATTR_RANDOM_BUILD_SIDE</keyword>
    <keyword>ATTR_RETREAT_VALUE</keyword>
    <keyword>ATTR_SHAMEN_BLAST</keyword>
    <keyword>ATTR_SPARE_6</keyword>
    <keyword>ATTR_SPELL_DELAY</keyword>
    <keyword>ATTR_SPY_CHECK_FREQUENCY</keyword>
    <keyword>ATTR_SPY_DISCOVER_CHANGE</keyword>
    <keyword>ATTR_USE_PREACHER_FOR_DEFENSE</keyword>
    <keyword>BALLON_TYPE</keyword>
    <keyword>BLAST</keyword>
    <keyword>BLOODLUST</keyword>
    <keyword>BLUE_KILLED_BY_ME</keyword>
    <keyword>BLUE_MANA</keyword>
    <keyword>BLUE_PEOPLE</keyword>
    <keyword>BOAT_HUT</keyword>
    <keyword>BOAT_HUT_2</keyword>
    <keyword>BOAT_TYPE</keyword>
    <keyword>BRAVE</keyword>
    <keyword>BUILDING_TYPE</keyword>
    <keyword>BURN</keyword>
    <keyword>B_BUILDING_AIRSHIP_HUT</keyword>
    <keyword>B_BUILDING_AIRSHIP_HUT_2</keyword>
    <keyword>B_BUILDING_BOAT_HUT</keyword>
    <keyword>B_BUILDING_BOAT_HUT_2</keyword>
    <keyword>B_BUILDING_CURR_OE_SLOT</keyword>
    <keyword>B_BUILDING_DRUM_TOWER</keyword>
    <keyword>B_BUILDING_FIREWARRIOR_TRAIN</keyword>
    <keyword>B_BUILDING_GATE</keyword>
    <keyword>B_BUILDING_LARGE_HUT</keyword>
    <keyword>B_BUILDING_MEDIUM_HUT</keyword>
    <keyword>B_BUILDING_RECONVERSION</keyword>
    <keyword>B_BUILDING_SMALL_HUT</keyword>
    <keyword>B_BUILDING_SPY_TRAIN</keyword>
    <keyword>B_BUILDING_TEMPLE</keyword>
    <keyword>B_BUILDING_WALL_PIECE</keyword>
    <keyword>B_BUILDING_WARRIOR_TRAIN</keyword>
    <keyword>B_PERSON_BRAVE</keyword>
    <keyword>B_PERSON_FIREWARRIOR</keyword>
    <keyword>B_PERSON_RELIGIOUS</keyword>
    <keyword>B_PERSON_SHAMAN</keyword>
    <keyword>B_PERSON_SPY</keyword>
    <keyword>B_PERSON_WARRIOR</keyword>
    <keyword>B_VEHICLE_AIRSHIP_1</keyword>
    <keyword>B_VEHICLE_BOAT_1</keyword>
    <keyword>CAMERA_ANGLE</keyword>
    <keyword>CAMERA_X</keyword>
    <keyword>CAMERA_Z</keyword>
    <keyword>CONVERT</keyword>
    <keyword>COUNT_WILD</keyword>
    <keyword>CP_FREE_ENTRIES</keyword>
    <keyword>DRUM_TOWER</keyword>
    <keyword>EARTHQUAKE</keyword>
    <keyword>EROSION</keyword>
    <keyword>FIRESTORM</keyword>
    <keyword>FIREWARRIOR</keyword>
    <keyword>FIREWARRIOR_TRAIN</keyword>
    <keyword>FLATTEN</keyword>
    <keyword>GAME_TURN</keyword>
    <keyword>GATE</keyword>
    <keyword>GHOST_ARMY</keyword>
    <keyword>GREEN_KILLED_BY_ME</keyword>
    <keyword>GREEN_MANA</keyword>
    <keyword>GREEN_PEOPLE</keyword>
    <keyword>GREEN_KILLED_BY_HUMAN</keyword>
    <keyword>GUARD_NORMAL</keyword>
    <keyword>GUARD_WITH_GHOSTS</keyword>
    <keyword>G_BUILDING_AIRSHIP_HUT</keyword>
    <keyword>G_BUILDING_AIRSHIP_HUT_2</keyword>
    <keyword>G_BUILDING_BOAT_HUT</keyword>
    <keyword>G_BUILDING_BOAT_HUT_2</keyword>
    <keyword>G_BUILDING_CURR_OE_SLOT</keyword>
    <keyword>G_BUILDING_DRUM_TOWER</keyword>
    <keyword>G_BUILDING_FIREWARRIOR_TRAIN</keyword>
    <keyword>G_BUILDING_GATE</keyword>
    <keyword>G_BUILDING_LARGE_HUT</keyword>
    <keyword>G_BUILDING_MEDIUM_HUT</keyword>
    <keyword>G_BUILDING_RECONVERSION</keyword>
    <keyword>G_BUILDING_SMALL_HUT</keyword>
    <keyword>G_BUILDING_SPY_TRAIN</keyword>
    <keyword>G_BUILDING_TEMPLE</keyword>
    <keyword>G_BUILDING_WALL_PIECE</keyword>
    <keyword>G_BUILDING_WARRIOR_TRAIN</keyword>
    <keyword>G_PERSON_BRAVE</keyword>
    <keyword>G_PERSON_FIREWARRIOR</keyword>
    <keyword>G_PERSON_RELIGIOUS</keyword>
    <keyword>G_PERSON_SHAMAN</keyword>
    <keyword>G_PERSON_SPY</keyword>
    <keyword>G_PERSON_WARRIOR</keyword>
    <keyword>G_VEHICLE_AIRSHIP_1</keyword>
    <keyword>G_VEHICLE_BOAT_1</keyword>
    <keyword>HYPNOTISM</keyword>
    <keyword>INSECT_PLAGUE</keyword>
    <keyword>INVISIBILITY</keyword>
    <keyword>LAND_BRIDGE</keyword>
    <keyword>LARGE_HUT</keyword>
    <keyword>LIGHTNING_BOLT</keyword>
    <keyword>MEDIUM_HUT</keyword>
    <keyword>MY_MANA</keyword>
    <keyword>MY_NUM_KILLED_BY_BLUE</keyword>
    <keyword>MY_NUM_KILLED_BY_GREEN</keyword>
    <keyword>MY_NUM_KILLED_BY_HUMAN</keyword>
    <keyword>MY_NUM_KILLED_BY_RED</keyword>
    <keyword>MY_NUM_KILLED_BY_YELLOW</keyword>
    <keyword>MY_NUM_PEOPLE</keyword>
    <keyword>M_BUILDING_AIRSHIP_HUT</keyword>
    <keyword>M_BUILDING_AIRSHIP_HUT_2</keyword>
    <keyword>M_BUILDING_BOAT_HUT</keyword>
    <keyword>M_BUILDING_BOAT_HUT_2</keyword>
    <keyword>M_BUILDING_CURR_OE_SLOT</keyword>
    <keyword>M_BUILDING_DRUM_TOWER</keyword>
    <keyword>M_BUILDING_FIREWARRIOR_TRAIN</keyword>
    <keyword>M_BUILDING_GATE</keyword>
    <keyword>M_BUILDING_LARGE_HUT</keyword>
    <keyword>M_BUILDING_MEDIUM_HUT</keyword>
    <keyword>M_BUILDING_RECONVERSION</keyword>
    <keyword>M_BUILDING_SMALL_HUT</keyword>
    <keyword>M_BUILDING_SPY_TRAIN</keyword>
    <keyword>M_BUILDING_TEMPLE</keyword>
    <keyword>M_BUILDING_WALL_PIECE</keyword>
    <keyword>M_BUILDING_WARRIOR_TRAIN</keyword>
    <keyword>M_PERSON_BRAVE</keyword>
    <keyword>M_PERSON_FIREWARRIOR</keyword>
    <keyword>M_PERSON_RELIGIOUS</keyword>
    <keyword>M_PERSON_SHAMAN</keyword>
    <keyword>M_PERSON_SPY</keyword>
    <keyword>M_PERSON_WARRIOR</keyword>
    <keyword>M_SPELL_SHIELD_COST</keyword>
    <keyword>M_SPEll_ANGEL_OF_DEAD_COST</keyword>
    <keyword>M_SPEll_BLAST_COST</keyword>
    <keyword>M_SPEll_BURN_COST</keyword>
    <keyword>M_SPEll_EARTHQUAKE_COST</keyword>
    <keyword>M_SPEll_EROSION_COST</keyword>
    <keyword>M_SPEll_FIRESTORM_COST</keyword>
    <keyword>M_SPEll_FLATTEN_COST</keyword>
    <keyword>M_SPEll_GHOST_ARMY_COST</keyword>
    <keyword>M_SPEll_HYPNOTISM_COST</keyword>
    <keyword>M_SPEll_INSECT_PLAGUE_COST</keyword>
    <keyword>M_SPEll_INVISIBILITY_COST</keyword>
    <keyword>M_SPEll_LAND_BRIDGE_COST</keyword>
    <keyword>M_SPEll_LIGHTNING_COST</keyword>
    <keyword>M_SPEll_SWAMP_COST</keyword>
    <keyword>M_SPEll_VOLCANO_COST</keyword>
    <keyword>M_SPEll_WHIRLMIND_COST</keyword>
    <keyword>M_SPEll_WRATH_OF_GOD_COST</keyword>
    <keyword>M_VEHICLE_AIRSHIP_1</keyword>
    <keyword>M_VEHICLE_BOAT_1</keyword>
    <keyword>NO_SPECIFIC_BUILDING</keyword>
    <keyword>NO_SPECIFIC_PERSON</keyword>
    <keyword>NO_SPECIFIC_SPELL</keyword>
    <keyword>NUM_SHAMEN_DEFENDERS</keyword>
    <keyword>RANDOM_100</keyword>
    <keyword>RECONVERSION</keyword>
    <keyword>RED_KILLED_BY_ME</keyword>
    <keyword>RED_MANA</keyword>
    <keyword>RED_PEOPLE</keyword>
    <keyword>RED_KILLED_BY_HUMAN</keyword>
    <keyword>RELIGIOUS</keyword>
    <keyword>R_BUILDING_AIRSHIP_HUT</keyword>
    <keyword>R_BUILDING_AIRSHIP_HUT_2</keyword>
    <keyword>R_BUILDING_BOAT_HUT</keyword>
    <keyword>R_BUILDING_BOAT_HUT_2</keyword>
    <keyword>R_BUILDING_CURR_OE_SLOT</keyword>
    <keyword>R_BUILDING_DRUM_TOWER</keyword>
    <keyword>R_BUILDING_FIREWARRIOR_TRAIN</keyword>
    <keyword>R_BUILDING_GATE</keyword>
    <keyword>R_BUILDING_LARGE_HUT</keyword>
    <keyword>R_BUILDING_MEDIUM_HUT</keyword>
    <keyword>R_BUILDING_RECONVERSION</keyword>
    <keyword>R_BUILDING_SMALL_HUT</keyword>
    <keyword>R_BUILDING_SPY_TRAIN</keyword>
    <keyword>R_BUILDING_TEMPLE</keyword>
    <keyword>R_BUILDING_WALL_PIECE</keyword>
    <keyword>R_BUILDING_WARRIOR_TRAIN</keyword>
    <keyword>R_PERSON_BRAVE</keyword>
    <keyword>R_PERSON_FIREWARRIOR</keyword>
    <keyword>R_PERSON_RELIGIOUS</keyword>
    <keyword>R_PERSON_SHAMAN</keyword>
    <keyword>R_PERSON_SPY</keyword>
    <keyword>R_PERSON_WARRIOR</keyword>
    <keyword>R_VEHICLE_AIRSHIP_1</keyword>
    <keyword>R_VEHICLE_BOAT_1</keyword>
    <keyword>SHAMAN</keyword>
    <keyword>SHIELD</keyword>
    <keyword>SMALL_HUT</keyword>
    <keyword>SPELL_TYPE</keyword>
    <keyword>SPY</keyword>
    <keyword>SPY_TRAIN</keyword>
    <keyword>SWAMP</keyword>
    <keyword>TARGET_SHAMAN</keyword>
    <keyword>TELEPORT</keyword>
    <keyword>TEMPLE</keyword>
    <keyword>TRIBE_BLUE</keyword>
    <keyword>TRIBE_GREEN</keyword>
    <keyword>TRIBE_RED</keyword>
    <keyword>TRIBE_YELLOW</keyword>
    <keyword>VOLCANO</keyword>
    <keyword>WALL_PIECE</keyword>
    <keyword>WARRIOR</keyword>
    <keyword>WARRIOR_TRAIN</keyword>
    <keyword>WHIRLWIND</keyword>
    <keyword>WILD_PEOPLE</keyword>
    <keyword>WRATH_OF_GOD</keyword>
    <keyword>YELLOW_KILLED_BY_ME</keyword>
    <keyword>YELLOW_MANA</keyword>
    <keyword>YELLOW_PEOPLE</keyword>
    <keyword>YELLOW_KILLED_BY_HUMAN</keyword>
    <keyword>Y_BUILDING_AIRSHIP_HUT</keyword>
    <keyword>Y_BUILDING_AIRSHIP_HUT_2</keyword>
    <keyword>Y_BUILDING_BOAT_HUT</keyword>
    <keyword>Y_BUILDING_BOAT_HUT_2</keyword>
    <keyword>Y_BUILDING_CURR_OE_SLOT</keyword>
    <keyword>Y_BUILDING_DRUM_TOWER</keyword>
    <keyword>Y_BUILDING_FIREWARRIOR_TRAIN</keyword>
    <keyword>Y_BUILDING_GATE</keyword>
    <keyword>Y_BUILDING_LARGE_HUT</keyword>
    <keyword>Y_BUILDING_MEDIUM_HUT</keyword>
    <keyword>Y_BUILDING_RECONVERSION</keyword>
    <keyword>Y_BUILDING_SMALL_HUT</keyword>
    <keyword>Y_BUILDING_SPY_TRAIN</keyword>
    <keyword>Y_BUILDING_TEMPLE</keyword>
    <keyword>Y_BUILDING_WALL_PIECE</keyword>
    <keyword>Y_BUILDING_WARRIOR_TRAIN</keyword>
    <keyword>Y_PERSON_BRAVE</keyword>
    <keyword>Y_PERSON_FIREWARRIOR</keyword>
    <keyword>Y_PERSON_RELIGIOUS</keyword>
    <keyword>Y_PERSON_SHAMAN</keyword>
    <keyword>Y_PERSON_SPY</keyword>
    <keyword>Y_PERSON_WARRIOR</keyword>
    <keyword>Y_VEHICLE_AIRSHIP_1</keyword>
    <keyword>Y_VEHICLE_BOAT_1</keyword>
  </keywords2>
  <dataTypes>
    <dataType>action</dataType>
    <dataType>attack_mode</dataType>
    <dataType>attack_target</dataType>
    <dataType>count_wild_t</dataType>
    <dataType>int</dataType>
    <dataType>shot_type</dataType>
    <dataType>state</dataType>
    <dataType>tribe</dataType>
    <dataType>vehicle_type</dataType>
  </dataTypes>
  <functions>
    <function>Attack</function>
    <function>AttackBlue</function>
    <function>AttackGreen</function>
    <function>AttackRed</function>
    <function>AttackYellow</function>
    <function>AutoAttack</function>
    <function>AutoMessages</function>
    <function>BoatPatrol</function>
    <function>BringNewPeopleBack</function>
    <function>BuildAt</function>
    <function>BuildDrumTower</function>
    <function>BuildMainDrumTower</function>
    <function>BuildOuterDefences</function>
    <function>BuildVehicle</function>
    <function>BuildWalls</function>
    <function>CallToArms</function>
    <function>CameraRotation</function>
    <function>CheckIfPersonPreachedTo</function>
    <function>ClearAllMsg</function>
    <function>ClearGuardingFrom</function>
    <function>ClearHouseInfoFlag</function>
    <function>ClearShamanLeftClick</function>
    <function>ClearShamanRightClick</function>
    <function>ClearStandingPeople</function>
    <function>ConstructBuilding</function>
    <function>ConvertAtMarker</function>
    <function>CountAngels</function>
    <function>CountBlueInHouses</function>
    <function>CountBlueShapes</function>
    <function>CountBlueWithBuildCommand</function>
    <function>CountGuardFires</function>
    <function>CountPeopleInMarker</function>
    <function>CreateMsgInformation</function>
    <function>CreateMsgInformationZoom</function>
    <function>CreateMsgNarrative</function>
    <function>CreateMsgObjective</function>
    <function>Defend</function>
    <function>DefendBase</function>
    <function>DefendShamen</function>
    <function>DelayMainDrumTower</function>
    <function>DeleteSmokeStuff</function>
    <function>DeselectAllBluePeople</function>
    <function>DisableUserInputs</function>
    <function>DontHouseSpecialists</function>
    <function>DontTargetBlueDrumTowers</function>
    <function>DontTargetBlueShaman</function>
    <function>DontTargetFirewarriors</function>
    <function>EnableShamanGetWilds</function>
    <function>EnableUserInputs</function>
    <function>ExtraWoodCollection</function>
    <function>FetchFarVehicle</function>
    <function>FetchLostPeople</function>
    <function>FetchLostVehicle</function>
    <function>FetchWood</function>
    <function>FirewarriorDefend</function>
    <function>FixWildInArea</function>
    <function>FlashButton</function>
    <function>FlattenBase</function>
    <function>FlybyAllowInterrupt</function>
    <function>FlybyCreateNew</function>
    <function>FlybySetEndTarget</function>
    <function>FlybySetEventAngle</function>
    <function>FlybySetEventIntPoint</function>
    <function>FlybySetEventPos</function>
    <function>FlybySetEventTooltip</function>
    <function>FlybySetEventZoom</function>
    <function>FlybySetMessage</function>
    <function>FlybyStart</function>
    <function>FlybyStop</function>
    <function>ForceTooltip</function>
    <function>GetHeadTriggerCount</function>
    <function>GetHeightAtPos</function>
    <function>GetMsgId</function>
    <function>GetNumOneOffSpells</function>
    <function>GetNumPeopleBeingPreached</function>
    <function>GetNumPeopleConverted</function>
    <function>GetSpellsCast</function>
    <function>GiveManaToPlayer</function>
    <function>GiveOneShot</function>
    <function>GivePlayerSpell</function>
    <function>GiveUpAndSulk</function>
    <function>GuardAtMarker</function>
    <function>GuardBetweenMarkers</function>
    <function>HasBlueKilledAGhost</function>
    <function>HasHouseInfoBeenShown</function>
    <function>HasPlayerBeenInEncyc</function>
    <function>HasTimerReachedZero</function>
    <function>HouseAPerson</function>
    <function>IHaveOneShot</function>
    <function>IsBlueShamanSelected</function>
    <function>IsBuildingNear</function>
    <function>IsPlayerInWorldView</function>
    <function>IsPrisonOnLevel</function>
    <function>IsShamanAvailableForAttack</function>
    <function>IsShamanIconLeftClicked</function>
    <function>IsShamanIconRightClicked</function>
    <function>IsShamanInArea</function>
    <function>KillAllMsgId</function>
    <function>KillTeamInArea</function>
    <function>MarkerEntries</function>
    <function>MarvellousHouseDeath</function>
    <function>MoveShamanToMarker</function>
    <function>NavCheck</function>
    <function>OnlyStandAtMarkers</function>
    <function>OpenDialog</function>
    <function>PartialBuildingCount</function>
    <function>PopulateDrumTower</function>
    <function>PrayAtHead</function>
    <function>Preach</function>
    <function>PreachAtMarker</function>
    <function>PutPersonInDrumTower</function>
    <function>RemoveHeadAtPos</function>
    <function>RemovePlayerThing</function>
    <function>RemoveTimer</function>
    <function>ResetBaseMarker</function>
    <function>ResetConvertMarker</function>
    <function>Sabotage</function>
    <function>SendAllPeopleToMarker</function>
    <function>SendBluePeopleToMarker</function>
    <function>SendGhostPeople</function>
    <function>SendGhosts</function>
    <function>SendShamenDefendersHome</function>
    <function>SetAttackVariable</function>
    <function>SetAutoBuild</function>
    <function>SetAutoHouse</function>
    <function>SetBaseMarker</function>
    <function>SetBaseRadious</function>
    <function>SetBucketCountForSpell</function>
    <function>SetBucketUsage</function>
    <function>SetBuildingDirection</function>
    <function>SetConvertMarker</function>
    <function>SetCreateReturnMsgOnRmbZoom</function>
    <function>SetDefenseRadius</function>
    <function>SetDrumTowerPos</function>
    <function>SetMarkerEntry</function>
    <function>SetMsgAutoOpenDlg</function>
    <function>SetMsgDeleteOnOk</function>
    <function>SetMsgDeleteOnRmbZoom</function>
    <function>SetMsgId</function>
    <function>SetMsgOkSaveExitDlg</function>
    <function>SetMsgOpenDlgOnRmbDelete</function>
    <function>SetMsgOpenDlgOnRmbZoom</function>
    <function>SetMsgReturnOnOk</function>
    <function>SetMsgTimeout</function>
    <function>SetMsgZoom</function>
    <function>SetMsgZoomOnLmbOpenDlg</function>
    <function>SetNoBlueReinc</function>
    <function>SetReincarnation</function>
    <function>SetSpecialNoBldgPanel</function>
    <function>SetSpellEntry</function>
    <function>SetTimerGoing</function>
    <function>SetWoodCollectionRadii</function>
    <function>ShamanDefend</function>
    <function>Spare10</function>
    <function>Spare5</function>
    <function>Spare6</function>
    <function>Spare7</function>
    <function>Spare8</function>
    <function>Spare9</function>
    <function>SpellAttack</function>
    <function>SpellDefence</function>
    <function>SpellOffensive</function>
    <function>StartReincNow</function>
    <function>StopCameraRotation</function>
    <function>TargetBlueDrumTowers</function>
    <function>TargetBlueShaman</function>
    <function>TargetPlayerDrumTowerAndFirewarrior</function>
    <function>TargetsFirewarriors</function>
    <function>TrackShamanExtraBollocks</function>
    <function>TrackShamanToAngle</function>
    <function>TrackToMarker</function>
    <function>TrainPeople</function>
    <function>TrainPeopleNow</function>
    <function>TriggerLevelLost</function>
    <function>TriggerLevelWon</function>
    <function>TriggerThing</function>
    <function>TurnPanelOn</function>
    <function>TurnPush</function>
    <function>ZoomTo</function>
  </functions>
  <numbers>
    <hexLiteral/>
    <intLiteral>{Digit}+</intLiteral>
    <floatLiteral/>
  </numbers>
  <stringLiterals enabled="true" multiLine="false"/>
  <charLiterals enabled="true" multiLine="false"/>
  <backtickLiterals enabled="false"/>
  <operators>
    <operator>!</operator>
    <operator>!=</operator>
    <operator>&amp;&amp;</operator>
    <operator>*</operator>
    <operator>*=</operator>
    <operator>+</operator>
    <operator>++</operator>
    <operator>+=</operator>
    <operator>-</operator>
    <operator>--</operator>
    <operator>-=</operator>
    <operator>/</operator>
    <operator>/=</operator>
    <operator>:</operator>
    <operator>&lt;</operator>
    <operator>&lt;=</operator>
    <operator>=</operator>
    <operator>==</operator>
    <operator>&gt;</operator>
    <operator>&gt;=</operator>
    <operator>?</operator>
    <operator>||</operator>
  </operators>
</TokenMakerDefinition>
